funding_arb/__init__.py
funding_arb/bb_bnc.py
funding_arb/bb_dtdc.py
funding_arb/bnc.py
funding_arb/bnc_dtdc.py
funding_arb/bybit.py
funding_arb/hyperliquid_v1.py
funding_arb/okx.py
funding_arb-0.1.3.dist-info/METADATA
funding_arb-0.1.3.dist-info/WHEEL
funding_arb-0.1.3.dist-info/RECORD
