Metadata-Version: 2.3
Name: funding-arb
Version: 0.1.3
Summary: Add your description here
Requires-Python: >=3.11
Classifier: Programming Language :: Python :: 3
Classifier: Programming Language :: Python :: 3.11
Classifier: Programming Language :: Python :: 3.12
Classifier: Programming Language :: Python :: 3.13
Requires-Dist: ccxt (>=4.4.93)
Requires-Dist: pandas (>=2.3.1)
Requires-Dist: tenacity (>=9.1.2)
Requires-Dist: throttled-py (>=2.2.1)
